<?xml version="1.0"?>
<itemListing>
    <item id="Apple">
        <canStack>true</canStack>
        <spriteIndex>0</spriteIndex>
        <components>
            <Usable />
            <Heal amount="10" />
        </components>
    </item>
    <item id="Banana">
        <canStack>true</canStack>
        <spriteIndex>1</spriteIndex>
        <components>
            <Usable />
            <Heal amount="5" />
        </components>
    </item>
    <item id="Heal_Potion">
        <canStack>true</canStack>
        <spriteIndex>2</spriteIndex>
        <components>
            <Usable />
            <Heal amount="50" />
        </components>
    </item>
    <item id="Regeneration_Potion">
        <canStack>true</canStack>
        <spriteIndex>3</spriteIndex>
        <components>
            <Usable />
            <Heal amount="120" />
        </components>
    </item>
    <item id="Wood">
        <canStack>true</canStack>
        <spriteIndex>4</spriteIndex>
        <components>
            
        </components>
    </item>
    <item id="Stone">
        <canStack>true</canStack>
        <spriteIndex>5</spriteIndex>
        <components>
            
        </components>
    </item>
    <item id="Common_Pickaxe">
        <canStack>false</canStack>
        <spriteIndex>6</spriteIndex>
        <components>
            
        </components>
    </item>
    <item id="Cactus">
        <canStack>false</canStack>
        <spriteIndex>7</spriteIndex>
        <components>
            
        </components>
    </item>
    <item id="Rope">
        <canStack>true</canStack>
        <spriteIndex>8</spriteIndex>
        <components>
            
        </components>
    </item>
    <item id="Common_Sword">
        <canStack>false</canStack>
        <spriteIndex>9</spriteIndex>
        <components>
            
        </components>
    </item>
    <item id="Grass">
        <canStack>true</canStack>
        <spriteIndex>10</spriteIndex>
        <components>
            
        </components>
    </item>
</itemListing>